{
  "project_info": {
    "project_number": "711897221217",
    "project_id": "peace-pulce",
    "storage_bucket": "peace-pulce.appspot.com"
  },
  "client": [
    {
      "client_info": {
        "mobilesdk_app_id": "1:711897221217:android:5772d50967bdb78ac00220",
        "android_client_info": {
          "package_name": "com.frontend"
        }
      },
      "oauth_client": [],
      "api_key": [
        {
          "current_key": "AIzaSyDBjjk0-Ak4CP4p3mIcObB7YbT9Kroq-9M"
        }
      ],
      "services": {
        "appinvite_service": {
          "other_platform_oauth_client": []
        }
      }
    }
  ],
  "configuration_version": "1"
}